tdmat/__init__.py
tdmat/_data/DHW_sizing/Peak power - 15 min.csv
tdmat/_data/DHW_sizing/Peak power - 3 min.csv
tdmat/_data/DHW_sizing/__init__.py
tdmat/_data/Tabula/Calc_Building_Set.csv
tdmat/_data/Tabula/Tab_Building.csv
tdmat/_data/Tabula/Tabula.zip
tdmat/_data/Tabula/__init__.py
tdmat/_data/__init__.py
tdmat/demand.py
tdmat/weather.py
tdmat-0.1.0.dist-info/LICENSE
tdmat-0.1.0.dist-info/WHEEL
tdmat-0.1.0.dist-info/METADATA
tdmat-0.1.0.dist-info/RECORD
